azure/storage/file/__init__.py
azure/storage/file/_constants.py
azure/storage/file/_deserialization.py
azure/storage/file/_download_chunking.py
azure/storage/file/_serialization.py
azure/storage/file/_upload_chunking.py
azure/storage/file/fileservice.py
azure/storage/file/models.py
azure/storage/file/sharedaccesssignature.py
azure_storage_file-2.0.1.dist-info/LICENSE.txt
azure_storage_file-2.0.1.dist-info/METADATA
azure_storage_file-2.0.1.dist-info/WHEEL
azure_storage_file-2.0.1.dist-info/top_level.txt
azure_storage_file-2.0.1.dist-info/RECORD
