Metadata-Version: 2.1
Name: azure-storage-file
Version: 2.0.1
Summary: Microsoft Azure Storage File Client Library for Python
Home-page: https://github.com/Azure/azure-storage-python
Author: Microsoft Corporation
Author-email: ascl@microsoft.com
License: MIT License
Platform: UNKNOWN
Classifier: Development Status :: 4 - Beta
Classifier: Programming Language :: Python
Classifier: Programming Language :: Python :: 2
Classifier: Programming Language :: Python :: 2.7
Classifier: Programming Language :: Python :: 3
Classifier: Programming Language :: Python :: 3.3
Classifier: Programming Language :: Python :: 3.4
Classifier: Programming Language :: Python :: 3.5
Classifier: Programming Language :: Python :: 3.6
Classifier: Programming Language :: Python :: 3.7
Classifier: License :: OSI Approved :: MIT License
Requires-Dist: azure-common (>=1.1.5)
Requires-Dist: azure-storage-common (~=2.0)
Requires-Dist: futures ; python_version<'3.0'
